{
    "processing_time": 26.951,
    "results": [
        {
            "box": {
                "xmin": 376,
                "ymin": 622,
                "xmax": 553,
                "ymax": 679
            },
            "plate": "g95045",
            "region": {
                "code": "cn",
                "score": 0.529
            },
            "score": 0.999,
            "candidates": [
                {
                    "score": 0.999,
                    "plate": "g95045"
                },
                {
                    "score": 0.841,
                    "plate": "g95o45"
                }
            ],
            "dscore": 0.825,
            "vehicle": {
                "score": 0.727,
                "type": "Van",
                "box": {
                    "xmin": 78,
                    "ymin": 0,
                    "xmax": 801,
                    "ymax": 726
                }
            }
        }
    ],
    "filename": "1352_kQoHJ_G1_187.jpg",
    "version": 1,
    "camera_id": null,
    "timestamp": "2024-12-03T13:52:29.860013Z",
    "image_width": 1082,
    "image_height": 727
}